samarium/__init__.py
samarium/__main__.py
samarium/builtins.py
samarium/classes/__init__.py
samarium/classes/base.py
samarium/classes/fileio.py
samarium/core.py
samarium/exceptions.py
samarium/imports.py
samarium/modules/collections.sm
samarium/modules/datetime.sm
samarium/modules/io.sm
samarium/modules/iter.sm
samarium/modules/math.sm
samarium/modules/operator.sm
samarium/modules/pystd.py
samarium/modules/random.sm
samarium/modules/string.sm
samarium/modules/types.sm
samarium/python.py
samarium/repl.py
samarium/runtime.py
samarium/template.txt
samarium/tokenizer.py
samarium/tokens.py
samarium/transpiler.py
samarium/utils.py
samarium-0.6.2.dist-info/LICENSE
samarium-0.6.2.dist-info/METADATA
samarium-0.6.2.dist-info/WHEEL
samarium-0.6.2.dist-info/entry_points.txt
samarium-0.6.2.dist-info/RECORD
