Metadata-Version: 2.1
Name: samarium
Version: 0.6.2
Summary: The Samarium Programming Language
Home-page: https://github.com/samarium-lang/Samarium
License: MIT
Author: trag1c
Author-email: trag1cdev@yahoo.com
Requires-Python: >=3.9,<4.0
Classifier: License :: OSI Approved :: MIT License
Classifier: Programming Language :: Python :: 3
Classifier: Programming Language :: Python :: 3.9
Classifier: Programming Language :: Python :: 3.10
Classifier: Programming Language :: Python :: 3.11
Classifier: Programming Language :: Python :: 3.12
Requires-Dist: crossandra (>=2.2.1,<3.0.0)
Requires-Dist: dahlia (>=3.0.0,<4.0.0)
Project-URL: Documentation, https://samarium-lang.github.io/Samarium/
Project-URL: Repository, https://github.com/samarium-lang/Samarium
